[
  {
    "model": "workflows.abstractwidget", 
    "fields": {
      "category": "46050a99-188d-40e1-90e5-0c1912059fa7", 
      "treeview_image": "", 
      "uid": "bbcab045-e896-4cb6-b111-c0324423367b", 
      "windows_queue": false, 
      "package": "nltoolkit", 
      "interaction_view": "", 
      "has_progress_bar": false, 
      "image": "", 
      "description": "Automatically generated widget from function TrainClassifier in package latino. The original function signature: TrainClassifier.", 
      "static_image": "classifier_train_image.png", 
      "action": "train_classifier", 
      "visualization_view": "", 
      "streaming_visualization_view": "", 
      "post_interact_action": "", 
      "wsdl_method": "", 
      "wsdl": "", 
      "interactive": false, 
      "is_streaming": false, 
      "order": 2, 
      "name": "Train Classifier Hub"
    }
  }, 
  {
    "model": "workflows.abstractinput", 
    "fields": {
      "widget": "bbcab045-e896-4cb6-b111-c0324423367b", 
      "name": "Dataset", 
      "short_name": "ds", 
      "default": "", 
      "description": "Latino.Model.LabeledDataset`2[[System.String, mscorlib, Version=4.0.0.0, Culture=neutral, PublicKeyToken=b77a5c561934e089],[Latino.SparseVector`1[[System.Double, mscorlib, Version=4.0.0.0, Culture=neutral, PublicKeyToken=b77a5c561934e089]], Latino, Version=1.0.0.0, Culture=neutral, PublicKeyToken=null]]", 
      "required": true, 
      "multi": false, 
      "parameter_type": null, 
      "variable": "training_data", 
      "parameter": false, 
      "order": 2, 
      "uid": "a1d6b382-7850-423d-8bdd-8f4fad43c9ec"
    }
  }, 
  {
    "model": "workflows.abstractinput", 
    "fields": {
      "widget": "bbcab045-e896-4cb6-b111-c0324423367b", 
      "name": "Classifier", 
      "short_name": "csf", 
      "default": "", 
      "description": "Latino.Model.IModel`1[[System.String, mscorlib, Version=4.0.0.0, Culture=neutral, PublicKeyToken=b77a5c561934e089]]", 
      "required": true, 
      "multi": false, 
      "parameter_type": null, 
      "variable": "classifier", 
      "parameter": false, 
      "order": 1, 
      "uid": "d483dc98-f0a1-4e60-af44-2ab085741966"
    }
  }, 
  {
    "model": "workflows.abstractoutput", 
    "fields": {
      "widget": "bbcab045-e896-4cb6-b111-c0324423367b", 
      "name": "Classifier", 
      "short_name": "csf", 
      "description": "", 
      "variable": "trained_classifier", 
      "order": 1, 
      "uid": "a2b2903a-3ca6-4854-9f1b-dc10fe353273"
    }
  }
]